LICENSE
README.md
package.json
requirements.txt
setup.py
fastapi_versionizer/__init__.py
fastapi_versionizer/py.typed
fastapi_versionizer/versionizer.py
fastapi_versionizer.egg-info/PKG-INFO
fastapi_versionizer.egg-info/SOURCES.txt
fastapi_versionizer.egg-info/dependency_links.txt
fastapi_versionizer.egg-info/requires.txt
fastapi_versionizer.egg-info/top_level.txt