Metadata-Version: 2.1
Name: fastapi-versionizer
Version: 4.0.2
Summary: API versionizer for FastAPI web applications
Home-page: https://github.com/alexschimpf/fastapi-versionizer
Author: Alex Schimpf
Author-email: aschimpf1@gmail.com
License: UNKNOWN
Platform: UNKNOWN
Classifier: Programming Language :: Python :: 3.8
Classifier: Programming Language :: Python :: 3.9
Classifier: Programming Language :: Python :: 3.10
Classifier: Programming Language :: Python :: 3.11
Classifier: Programming Language :: Python :: 3.12
Classifier: Programming Language :: Python :: 3.13
Requires-Python: >=3.8
